COPYING
COPYING.LESSER
MANIFEST.in
VERSION
requirements.django.txt
requirements.txt
setup.py
test-requirements.txt
tox.ini
zetup.cfg
jinjatools/__init__.py
jinjatools/conftest.py
jinjatools/env.py
jinjatools/ext.py
jinjatools/filters.py
jinjatools/zetup_config.py
jinjatools.egg-info/PKG-INFO
jinjatools.egg-info/SOURCES.txt
jinjatools.egg-info/dependency_links.txt
jinjatools.egg-info/requires.txt
jinjatools.egg-info/top_level.txt
jinjatools/django/__init__.py
jinjatools/scons/__init__.py
test/conftest.py
test/test_jinjatools.py