Metadata-Version: 2.1
Name: jinjatools
Version: 0.1.9
Summary: Various tools for Jinja2, including new filters and tests based on moretools, a JinjaLoader class for Django, and a simple JinjaBuilder class for SCons.
Home-page: http://github.com/zimmermanncode/jinjatools
Author: Stefan Zimmermann
Author-email: user@zimmermann.co
License: LGPLv3
Keywords: jinja,jinja2,tools,template,macro,filter,test,moretools,scons,builder,build,django,web,html,python3
Platform: UNKNOWN
Classifier: Development Status :: 3 - Alpha
Classifier: Intended Audience :: Developers
Classifier: License :: OSI Approved :: GNU Library or Lesser General Public License (LGPL)
Classifier: Operating System :: OS Independent
Classifier: Topic :: Software Development
Classifier: Topic :: Utilities
Classifier: Programming Language :: Python
Classifier: Programming Language :: Python :: 2
Classifier: Programming Language :: Python :: 2.7
Classifier: Programming Language :: Python :: 3
Classifier: Programming Language :: Python :: 3.5
Classifier: Programming Language :: Python :: 3.6
Classifier: Programming Language :: Python :: 3.7
Provides-Extra: all
Provides-Extra: django
